{
  "rca": [
    {
      "kind": "unit",
      "name": "./alacritty_terminal/src/config/scrolling.rs",
      "start_line": 1,
      "end_line": 59,
      "data": {
        "nargs": {
          "sum": 4.0,
          "average": 0.8
        },
        "nexits": {
          "sum": 4.0,
          "average": 0.8
        },
        "cognitive": {
          "sum": 2.0,
          "average": 0.4
        },
        "cyclomatic": {
          "sum": 15.0,
          "average": 1.5
        },
        "halstead": {
          "n1": 19.0,
          "N1": 96.0,
          "n2": 36.0,
          "N2": 63.0,
          "length": 159.0,
          "estimated_program_length": 266.82792280735134,
          "purity_ratio": 1.6781630365242224,
          "vocabulary": 55.0,
          "volume": 919.236194450421,
          "difficulty": 16.625,
          "level": 0.06015037593984962,
          "effort": 15282.301732738248,
          "time": 849.0167629299026,
          "bugs": 0.20527588130778615
        },
        "loc": {
          "sloc": 59.0,
          "ploc": 45.0,
          "lloc": 8.0,
          "cloc": 3.0,
          "blank": 11.0
        },
        "nom": {
          "functions": 5.0,
          "closures": 0.0,
          "total": 5.0
        },
        "mi": {
          "mi_original": 66.01146927940223,
          "mi_sei": 38.17444751614541,
          "mi_visual_studio": 38.60319840900715
        }
      }
    },
    {
      "kind": "impl",
      "name": "ScrollingHistory",
      "start_line": 43,
      "end_line": 59,
      "data": {
        "nargs": {
          "sum": 1.0,
          "average": 1.0
        },
        "nexits": {
          "sum": 1.0,
          "average": 1.0
        },
        "cognitive": {
          "sum": 2.0,
          "average": 2.0
        },
        "cyclomatic": {
          "sum": 5.0,
          "average": 2.5
        },
        "halstead": {
          "n1": 14.0,
          "N1": 33.0,
          "n2": 14.0,
          "N2": 22.0,
          "length": 55.0,
          "estimated_program_length": 106.60593781761293,
          "purity_ratio": 1.938289778502053,
          "vocabulary": 28.0,
          "volume": 264.4045207131682,
          "difficulty": 11.0,
          "level": 0.09090909090909093,
          "effort": 2908.4497278448503,
          "time": 161.580540435825,
          "bugs": 0.06791824463618704
        },
        "loc": {
          "sloc": 17.0,
          "ploc": 16.0,
          "lloc": 4.0,
          "cloc": 0.0,
          "blank": 1.0
        },
        "nom": {
          "functions": 1.0,
          "closures": 0.0,
          "total": 1.0
        },
        "mi": {
          "mi_original": 94.9490467559275,
          "mi_sei": 61.790766196920515,
          "mi_visual_studio": 55.52575833679971
        }
      }
    },
    {
      "kind": "function",
      "name": "deserialize",
      "start_line": 44,
      "end_line": 58,
      "data": {
        "nargs": {
          "sum": 1.0,
          "average": 1.0
        },
        "nexits": {
          "sum": 1.0,
          "average": 1.0
        },
        "cognitive": {
          "sum": 2.0,
          "average": 2.0
        },
        "cyclomatic": {
          "sum": 3.0,
          "average": 3.0
        },
        "halstead": {
          "n1": 13.0,
          "N1": 27.0,
          "n2": 14.0,
          "N2": 20.0,
          "length": 47.0,
          "estimated_program_length": 101.40868524464064,
          "purity_ratio": 2.157631600949801,
          "vocabulary": 27.0,
          "volume": 223.47971260168305,
          "difficulty": 9.285714285714286,
          "level": 0.10769230769230768,
          "effort": 2075.1687598727713,
          "time": 115.28715332626508,
          "bugs": 0.05423100995766033
        },
        "loc": {
          "sloc": 15.0,
          "ploc": 14.0,
          "lloc": 4.0,
          "cloc": 0.0,
          "blank": 1.0
        },
        "nom": {
          "functions": 1.0,
          "closures": 0.0,
          "total": 1.0
        },
        "mi": {
          "mi_original": 98.31111942154624,
          "mi_sei": 66.43757203990805,
          "mi_visual_studio": 57.49188270265862
        }
      }
    },
    {
      "kind": "impl",
      "name": "ScrollingHistory",
      "start_line": 37,
      "end_line": 41,
      "data": {
        "nargs": {
          "sum": 0.0,
          "average": 0.0
        },
        "nexits": {
          "sum": 1.0,
          "average": 1.0
        },
        "cognitive": {
          "sum": 0.0,
          "average": 0.0
        },
        "cyclomatic": {
          "sum": 3.0,
          "average": 1.5
        },
        "halstead": {
          "n1": 5.0,
          "N1": 7.0,
          "n2": 3.0,
          "N2": 3.0,
          "length": 10.0,
          "estimated_program_length": 16.36452797660028,
          "purity_ratio": 1.6364527976600278,
          "vocabulary": 8.0,
          "volume": 30.0,
          "difficulty": 2.5,
          "level": 0.4,
          "effort": 75.0,
          "time": 4.166666666666667,
          "bugs": 0.005928155507483437
        },
        "loc": {
          "sloc": 5.0,
          "ploc": 5.0,
          "lloc": 1.0,
          "cloc": 0.0,
          "blank": 0.0
        },
        "nom": {
          "functions": 1.0,
          "closures": 0.0,
          "total": 1.0
        },
        "mi": {
          "mi_original": 126.55087943392437,
          "mi_sei": 107.17893376566045,
          "mi_visual_studio": 74.00636224206103
        }
      }
    },
    {
      "kind": "function",
      "name": "default",
      "start_line": 38,
      "end_line": 40,
      "data": {
        "nargs": {
          "sum": 0.0,
          "average": 0.0
        },
        "nexits": {
          "sum": 1.0,
          "average": 1.0
        },
        "cognitive": {
          "sum": 0.0,
          "average": 0.0
        },
        "cyclomatic": {
          "sum": 1.0,
          "average": 1.0
        },
        "halstead": {
          "n1": 4.0,
          "N1": 5.0,
          "n2": 3.0,
          "N2": 3.0,
          "length": 8.0,
          "estimated_program_length": 12.754887502163468,
          "purity_ratio": 1.5943609377704335,
          "vocabulary": 7.0,
          "volume": 22.458839376460833,
          "difficulty": 2.0,
          "level": 0.5,
          "effort": 44.91767875292167,
          "time": 2.495426597384537,
          "bugs": 0.00421201861424495
        },
        "loc": {
          "sloc": 3.0,
          "ploc": 3.0,
          "lloc": 1.0,
          "cloc": 0.0,
          "blank": 0.0
        },
        "nom": {
          "functions": 1.0,
          "closures": 0.0,
          "total": 1.0
        },
        "mi": {
          "mi_original": 136.7917227048098,
          "mi_sei": 121.74970784827904,
          "mi_visual_studio": 79.99515947649695
        }
      }
    },
    {
      "kind": "impl",
      "name": "Scrolling",
      "start_line": 23,
      "end_line": 32,
      "data": {
        "nargs": {
          "sum": 3.0,
          "average": 1.5
        },
        "nexits": {
          "sum": 1.0,
          "average": 0.5
        },
        "cognitive": {
          "sum": 0.0,
          "average": 0.0
        },
        "cyclomatic": {
          "sum": 3.0,
          "average": 1.0
        },
        "halstead": {
          "n1": 11.0,
          "N1": 19.0,
          "n2": 5.0,
          "N2": 10.0,
          "length": 29.0,
          "estimated_program_length": 49.66338827944708,
          "purity_ratio": 1.7125306303257612,
          "vocabulary": 16.0,
          "volume": 116.0,
          "difficulty": 11.0,
          "level": 0.09090909090909093,
          "effort": 1276.0,
          "time": 70.88888888888889,
          "bugs": 0.03921442592027817
        },
        "loc": {
          "sloc": 10.0,
          "ploc": 8.0,
          "lloc": 2.0,
          "cloc": 1.0,
          "blank": 1.0
        },
        "nom": {
          "functions": 2.0,
          "closures": 0.0,
          "total": 2.0
        },
        "mi": {
          "mi_original": 108.28945249974338,
          "mi_sei": 104.36005580710632,
          "mi_visual_studio": 63.32716520452829
        }
      }
    },
    {
      "kind": "function",
      "name": "set_history",
      "start_line": 29,
      "end_line": 31,
      "data": {
        "nargs": {
          "sum": 2.0,
          "average": 2.0
        },
        "nexits": {
          "sum": 0.0,
          "average": 0.0
        },
        "cognitive": {
          "sum": 0.0,
          "average": 0.0
        },
        "cyclomatic": {
          "sum": 1.0,
          "average": 1.0
        },
        "halstead": {
          "n1": 10.0,
          "N1": 11.0,
          "n2": 4.0,
          "N2": 6.0,
          "length": 17.0,
          "estimated_program_length": 41.219280948873624,
          "purity_ratio": 2.42466358522786,
          "vocabulary": 14.0,
          "volume": 64.72503367497927,
          "difficulty": 7.5,
          "level": 0.13333333333333333,
          "effort": 485.43775256234454,
          "time": 26.968764031241363,
          "bugs": 0.02058896162987345
        },
        "loc": {
          "sloc": 3.0,
          "ploc": 3.0,
          "lloc": 2.0,
          "cloc": 0.0,
          "blank": 0.0
        },
        "nom": {
          "functions": 1.0,
          "closures": 0.0,
          "total": 1.0
        },
        "mi": {
          "mi_original": 131.28771108481735,
          "mi_sei": 113.8090975791207,
          "mi_visual_studio": 76.77643923088733
        }
      }
    },
    {
      "kind": "function",
      "name": "history",
      "start_line": 24,
      "end_line": 26,
      "data": {
        "nargs": {
          "sum": 1.0,
          "average": 1.0
        },
        "nexits": {
          "sum": 1.0,
          "average": 1.0
        },
        "cognitive": {
          "sum": 0.0,
          "average": 0.0
        },
        "cyclomatic": {
          "sum": 1.0,
          "average": 1.0
        },
        "halstead": {
          "n1": 6.0,
          "N1": 7.0,
          "n2": 3.0,
          "N2": 4.0,
          "length": 11.0,
          "estimated_program_length": 20.264662506490403,
          "purity_ratio": 1.842242046044582,
          "vocabulary": 9.0,
          "volume": 34.86917501586544,
          "difficulty": 4.0,
          "level": 0.25,
          "effort": 139.47670006346175,
          "time": 7.748705559081208,
          "bugs": 0.008964922118925448
        },
        "loc": {
          "sloc": 3.0,
          "ploc": 3.0,
          "lloc": 0.0,
          "cloc": 0.0,
          "blank": 0.0
        },
        "nom": {
          "functions": 1.0,
          "closures": 0.0,
          "total": 1.0
        },
        "mi": {
          "mi_original": 134.50414427548188,
          "mi_sei": 118.44942979264312,
          "mi_visual_studio": 78.65739431314731
        }
      }
    },
    {
      "kind": "impl",
      "name": "Scrolling",
      "start_line": 17,
      "end_line": 21,
      "data": {
        "nargs": {
          "sum": 0.0,
          "average": 0.0
        },
        "nexits": {
          "sum": 1.0,
          "average": 1.0
        },
        "cognitive": {
          "sum": 0.0,
          "average": 0.0
        },
        "cyclomatic": {
          "sum": 3.0,
          "average": 1.5
        },
        "halstead": {
          "n1": 6.0,
          "N1": 9.0,
          "n2": 3.0,
          "N2": 4.0,
          "length": 13.0,
          "estimated_program_length": 20.264662506490403,
          "purity_ratio": 1.558820192806954,
          "vocabulary": 9.0,
          "volume": 41.209025018750054,
          "difficulty": 4.0,
          "level": 0.25,
          "effort": 164.83610007500022,
          "time": 9.15756111527779,
          "bugs": 0.010021059309285525
        },
        "loc": {
          "sloc": 5.0,
          "ploc": 5.0,
          "lloc": 1.0,
          "cloc": 0.0,
          "blank": 0.0
        },
        "nom": {
          "functions": 1.0,
          "closures": 0.0,
          "total": 1.0
        },
        "mi": {
          "mi_original": 124.9000879302244,
          "mi_sei": 104.79734504973084,
          "mi_visual_studio": 73.04098709369848
        }
      }
    },
    {
      "kind": "function",
      "name": "default",
      "start_line": 18,
      "end_line": 20,
      "data": {
        "nargs": {
          "sum": 0.0,
          "average": 0.0
        },
        "nexits": {
          "sum": 1.0,
          "average": 1.0
        },
        "cognitive": {
          "sum": 0.0,
          "average": 0.0
        },
        "cyclomatic": {
          "sum": 1.0,
          "average": 1.0
        },
        "halstead": {
          "n1": 5.0,
          "N1": 7.0,
          "n2": 3.0,
          "N2": 4.0,
          "length": 11.0,
          "estimated_program_length": 16.36452797660028,
          "purity_ratio": 1.4876843615091162,
          "vocabulary": 8.0,
          "volume": 33.0,
          "difficulty": 3.3333333333333335,
          "level": 0.3,
          "effort": 110.0,
          "time": 6.111111111111111,
          "bugs": 0.007652568082218515
        },
        "loc": {
          "sloc": 3.0,
          "ploc": 3.0,
          "lloc": 1.0,
          "cloc": 0.0,
          "blank": 0.0
        },
        "nom": {
          "functions": 1.0,
          "closures": 0.0,
          "total": 1.0
        },
        "mi": {
          "mi_original": 134.79064160395092,
          "mi_sei": 118.86275806765332,
          "mi_visual_studio": 78.82493661049762
        }
      }
    }
  ],
  "node": [
    {
      "kind": "unit",
      "name": "./alacritty_terminal/src/config/scrolling.rs",
      "start_line": 1,
      "end_line": 59,
      "data": {
        "nargs": {
          "sum": 4.0,
          "average": 0.8
        },
        "nexits": {
          "sum": 4.0,
          "average": 0.8
        },
        "cognitive": {
          "sum": 2.0,
          "average": 0.4
        },
        "cyclomatic": {
          "sum": 14.0,
          "average": 1.5555555555555556
        },
        "halstead": {
          "n1": 19.0,
          "N1": 96.0,
          "n2": 36.0,
          "N2": 63.0,
          "length": 159.0,
          "estimated_program_length": 266.82792280735134,
          "purity_ratio": 1.6781630365242224,
          "vocabulary": 55.0,
          "volume": 919.236194450421,
          "difficulty": 16.625,
          "level": 0.06015037593984962,
          "effort": 15282.301732738248,
          "time": 849.0167629299026,
          "bugs": 0.20527588130778615
        },
        "loc": {
          "sloc": 15.0,
          "ploc": 45.0,
          "lloc": 8.0,
          "cloc": 3.0,
          "blank": -33.0
        },
        "nom": {
          "functions": 5.0,
          "closures": 0.0,
          "total": 5.0
        },
        "mi": {
          "mi_original": 88.42716261281907,
          "mi_sei": 85.23354555389602,
          "mi_visual_studio": 51.711791001648585
        }
      }
    },
    {
      "kind": "unknown",
      "name": "macro_invocation",
      "start_line": 51,
      "end_line": 54,
      "data": {
        "nargs": {
          "sum": 0.0,
          "average": null
        },
        "nexits": {
          "sum": 0.0,
          "average": null
        },
        "cognitive": {
          "sum": 0.0,
          "average": null
        },
        "cyclomatic": {
          "sum": 1.0,
          "average": 1.0
        },
        "halstead": {
          "n1": 2.0,
          "N1": 2.0,
          "n2": 4.0,
          "N2": 4.0,
          "length": 6.0,
          "estimated_program_length": 10.0,
          "purity_ratio": 1.6666666666666667,
          "vocabulary": 6.0,
          "volume": 15.509775004326936,
          "difficulty": 1.0,
          "level": 1.0,
          "effort": 15.509775004326936,
          "time": 0.861654166907052,
          "bugs": 0.0020730784816858556
        },
        "loc": {
          "sloc": 1.0,
          "ploc": 4.0,
          "lloc": 0.0,
          "cloc": 0.0,
          "blank": -3.0
        },
        "nom": {
          "functions": 0.0,
          "closures": 0.0,
          "total": 0.0
        },
        "mi": {
          "mi_original": 156.51435355291963,
          "mi_sei": 150.2034495661308,
          "mi_visual_studio": 91.5288617268536
        }
      }
    },
    {
      "kind": "unknown",
      "name": "where_clause",
      "start_line": 45,
      "end_line": 46,
      "data": {
        "nargs": {
          "sum": 0.0,
          "average": null
        },
        "nexits": {
          "sum": 0.0,
          "average": null
        },
        "cognitive": {
          "sum": 0.0,
          "average": null
        },
        "cyclomatic": {
          "sum": 5.0,
          "average": 1.0
        },
        "halstead": {
          "n1": 3.0,
          "N1": 3.0,
          "n2": 1.0,
          "N2": 1.0,
          "length": 4.0,
          "estimated_program_length": 4.754887502163468,
          "purity_ratio": 1.188721875540867,
          "vocabulary": 4.0,
          "volume": 8.0,
          "difficulty": 1.5,
          "level": 0.6666666666666666,
          "effort": 12.0,
          "time": 0.6666666666666666,
          "bugs": 0.0017471609294725976
        },
        "loc": {
          "sloc": 1.0,
          "ploc": 2.0,
          "lloc": 0.0,
          "cloc": 0.0,
          "blank": -1.0
        },
        "nom": {
          "functions": 0.0,
          "closures": 0.0,
          "total": 0.0
        },
        "mi": {
          "mi_original": 159.03690398326484,
          "mi_sei": 154.25,
          "mi_visual_studio": 93.00403741711392
        }
      }
    },
    {
      "kind": "unknown",
      "name": "where_predicate",
      "start_line": 46,
      "end_line": 46,
      "data": {
        "nargs": {
          "sum": 0.0,
          "average": null
        },
        "nexits": {
          "sum": 0.0,
          "average": null
        },
        "cognitive": {
          "sum": 0.0,
          "average": null
        },
        "cyclomatic": {
          "sum": 3.0,
          "average": 1.0
        },
        "halstead": {
          "n1": 2.0,
          "N1": 2.0,
          "n2": 1.0,
          "N2": 1.0,
          "length": 3.0,
          "estimated_program_length": 2.0,
          "purity_ratio": 0.6666666666666666,
          "vocabulary": 3.0,
          "volume": 4.754887502163468,
          "difficulty": 1.0,
          "level": 1.0,
          "effort": 4.754887502163468,
          "time": 0.26416041678685936,
          "bugs": 0.0009425525573729414
        },
        "loc": {
          "sloc": 1.0,
          "ploc": 1.0,
          "lloc": 0.0,
          "cloc": 0.0,
          "blank": 0.0
        },
        "nom": {
          "functions": 0.0,
          "closures": 0.0,
          "total": 0.0
        },
        "mi": {
          "mi_original": 162.20230020829433,
          "mi_sei": 158.61306171748976,
          "mi_visual_studio": 94.85514632063996
        }
      }
    },
    {
      "kind": "unknown",
      "name": "trait_bounds",
      "start_line": 46,
      "end_line": 46,
      "data": {
        "nargs": {
          "sum": 0.0,
          "average": null
        },
        "nexits": {
          "sum": 0.0,
          "average": null
        },
        "cognitive": {
          "sum": 0.0,
          "average": null
        },
        "cyclomatic": {
          "sum": 2.0,
          "average": 1.0
        },
        "halstead": {
          "n1": 2.0,
          "N1": 2.0,
          "n2": 1.0,
          "N2": 1.0,
          "length": 3.0,
          "estimated_program_length": 2.0,
          "purity_ratio": 0.6666666666666666,
          "vocabulary": 3.0,
          "volume": 4.754887502163468,
          "difficulty": 1.0,
          "level": 1.0,
          "effort": 4.754887502163468,
          "time": 0.26416041678685936,
          "bugs": 0.0009425525573729414
        },
        "loc": {
          "sloc": 1.0,
          "ploc": 1.0,
          "lloc": 0.0,
          "cloc": 0.0,
          "blank": 0.0
        },
        "nom": {
          "functions": 0.0,
          "closures": 0.0,
          "total": 0.0
        },
        "mi": {
          "mi_original": 162.43230020829432,
          "mi_sei": 158.84306171748975,
          "mi_visual_studio": 94.98964924461656
        }
      }
    },
    {
      "kind": "unknown",
      "name": "lifetime",
      "start_line": 46,
      "end_line": 46,
      "data": {
        "nargs": {
          "sum": 0.0,
          "average": null
        },
        "nexits": {
          "sum": 0.0,
          "average": null
        },
        "cognitive": {
          "sum": 0.0,
          "average": null
        },
        "cyclomatic": {
          "sum": 1.0,
          "average": 1.0
        },
        "halstead": {
          "n1": 0.0,
          "N1": 0.0,
          "n2": 1.0,
          "N2": 1.0,
          "length": 1.0,
          "estimated_program_length": null,
          "purity_ratio": null,
          "vocabulary": 1.0,
          "volume": 0.0,
          "difficulty": 0.0,
          "level": null,
          "effort": 0.0,
          "time": 0.0,
          "bugs": 0.0
        },
        "loc": {
          "sloc": 1.0,
          "ploc": 1.0,
          "lloc": 0.0,
          "cloc": 0.0,
          "blank": 0.0
        },
        "nom": {
          "functions": 0.0,
          "closures": 0.0,
          "total": 0.0
        },
        "mi": {
          "mi_original": null,
          "mi_sei": null,
          "mi_visual_studio": null
        }
      }
    },
    {
      "kind": "unknown",
      "name": "where",
      "start_line": 45,
      "end_line": 45,
      "data": {
        "nargs": {
          "sum": 0.0,
          "average": null
        },
        "nexits": {
          "sum": 0.0,
          "average": null
        },
        "cognitive": {
          "sum": 0.0,
          "average": null
        },
        "cyclomatic": {
          "sum": 1.0,
          "average": 1.0
        },
        "halstead": {
          "n1": 0.0,
          "N1": 0.0,
          "n2": 0.0,
          "N2": 0.0,
          "length": 0.0,
          "estimated_program_length": null,
          "purity_ratio": null,
          "vocabulary": 0.0,
          "volume": null,
          "difficulty": null,
          "level": null,
          "effort": null,
          "time": null,
          "bugs": null
        },
        "loc": {
          "sloc": 1.0,
          "ploc": 1.0,
          "lloc": 0.0,
          "cloc": 0.0,
          "blank": 0.0
        },
        "nom": {
          "functions": 0.0,
          "closures": 0.0,
          "total": 0.0
        },
        "mi": {
          "mi_original": null,
          "mi_sei": null,
          "mi_visual_studio": 0.0
        }
      }
    },
    {
      "kind": "unknown",
      "name": "lifetime",
      "start_line": 43,
      "end_line": 43,
      "data": {
        "nargs": {
          "sum": 0.0,
          "average": null
        },
        "nexits": {
          "sum": 0.0,
          "average": null
        },
        "cognitive": {
          "sum": 0.0,
          "average": null
        },
        "cyclomatic": {
          "sum": 1.0,
          "average": 1.0
        },
        "halstead": {
          "n1": 0.0,
          "N1": 0.0,
          "n2": 1.0,
          "N2": 1.0,
          "length": 1.0,
          "estimated_program_length": null,
          "purity_ratio": null,
          "vocabulary": 1.0,
          "volume": 0.0,
          "difficulty": 0.0,
          "level": null,
          "effort": 0.0,
          "time": 0.0,
          "bugs": 0.0
        },
        "loc": {
          "sloc": 1.0,
          "ploc": 1.0,
          "lloc": 0.0,
          "cloc": 0.0,
          "blank": 0.0
        },
        "nom": {
          "functions": 0.0,
          "closures": 0.0,
          "total": 0.0
        },
        "mi": {
          "mi_original": null,
          "mi_sei": null,
          "mi_visual_studio": null
        }
      }
    },
    {
      "kind": "unknown",
      "name": "lifetime",
      "start_line": 43,
      "end_line": 43,
      "data": {
        "nargs": {
          "sum": 0.0,
          "average": null
        },
        "nexits": {
          "sum": 0.0,
          "average": null
        },
        "cognitive": {
          "sum": 0.0,
          "average": null
        },
        "cyclomatic": {
          "sum": 1.0,
          "average": 1.0
        },
        "halstead": {
          "n1": 0.0,
          "N1": 0.0,
          "n2": 1.0,
          "N2": 1.0,
          "length": 1.0,
          "estimated_program_length": null,
          "purity_ratio": null,
          "vocabulary": 1.0,
          "volume": 0.0,
          "difficulty": 0.0,
          "level": null,
          "effort": 0.0,
          "time": 0.0,
          "bugs": 0.0
        },
        "loc": {
          "sloc": 1.0,
          "ploc": 1.0,
          "lloc": 0.0,
          "cloc": 0.0,
          "blank": 0.0
        },
        "nom": {
          "functions": 0.0,
          "closures": 0.0,
          "total": 0.0
        },
        "mi": {
          "mi_original": null,
          "mi_sei": null,
          "mi_visual_studio": null
        }
      }
    }
  ],
  "finder": [
    {
      "kind": "129",
      "name": "line_comment",
      "start_line": 6,
      "end_line": 6,
      "data": null
    },
    {
      "kind": "129",
      "name": "line_comment",
      "start_line": 9,
      "end_line": 9,
      "data": null
    },
    {
      "kind": "129",
      "name": "line_comment",
      "start_line": 28,
      "end_line": 28,
      "data": null
    },
    {
      "kind": "201",
      "name": "lifetime",
      "start_line": 43,
      "end_line": 43,
      "data": null
    },
    {
      "kind": "201",
      "name": "lifetime",
      "start_line": 43,
      "end_line": 43,
      "data": null
    },
    {
      "kind": "173",
      "name": "where_clause",
      "start_line": 45,
      "end_line": 46,
      "data": null
    },
    {
      "kind": "74",
      "name": "where",
      "start_line": 45,
      "end_line": 45,
      "data": null
    },
    {
      "kind": "174",
      "name": "where_predicate",
      "start_line": 46,
      "end_line": 46,
      "data": null
    },
    {
      "kind": "178",
      "name": "trait_bounds",
      "start_line": 46,
      "end_line": 46,
      "data": null
    },
    {
      "kind": "201",
      "name": "lifetime",
      "start_line": 46,
      "end_line": 46,
      "data": null
    },
    {
      "kind": "219",
      "name": "macro_invocation",
      "start_line": 51,
      "end_line": 54,
      "data": null
    }
  ],
  "clippy": []
}